{
  "timestamp": "2026-07-17T17:06:54.877983+00:00",
  "mode": "full_universe",
  "universe_size": 503,
  "market_open": true,
  "market_regime": "normal",
  "rsi_signals": [
    {
      "ticker": "SPY",
      "action": "HOLD",
      "price": 746.8800048828125,
      "rsi": 40.12,
      "ema_trend": "BEARISH",
      "bb_signal": "BELOW_BAND",
      "confidence": 0,
      "atr_pct": 0.004,
      "reason": "low volume (0.35x avg) \u2014 skipping",
      "fib_target": null,
      "rl_action": null,
      "rl_confidence": null
    },
    {
      "ticker": "QQQ",
      "action": "HOLD",
      "price": 701.6699829101562,
      "rsi": 38.62,
      "ema_trend": "BEARISH",
      "bb_signal": "IN_BAND",
      "confidence": 0,
      "atr_pct": 0.0084,
      "reason": "low volume (0.61x avg) \u2014 skipping",
      "fib_target": null,
      "rl_action": null,
      "rl_confidence": null
    },
    {
      "ticker": "IWM",
      "action": "HOLD",
      "price": 295.2408142089844,
      "rsi": 49.64,
      "ema_trend": "NEUTRAL",
      "bb_signal": "IN_BAND",
      "confidence": 0,
      "atr_pct": 0.0057,
      "reason": "low volume (0.21x avg) \u2014 skipping",
      "fib_target": null,
      "rl_action": null,
      "rl_confidence": null
    },
    {
      "ticker": "AAPL",
      "action": "HOLD",
      "price": 330.0400085449219,
      "rsi": 58.5,
      "ema_trend": "BULLISH",
      "bb_signal": "IN_BAND",
      "confidence": 0,
      "atr_pct": 0.0112,
      "reason": "low volume (0.51x avg) \u2014 skipping",
      "fib_target": null,
      "rl_action": null,
      "rl_confidence": null
    },
    {
      "ticker": "MSFT",
      "action": "HOLD",
      "price": 394.4150085449219,
      "rsi": 50.31,
      "ema_trend": "BULLISH",
      "bb_signal": "IN_BAND",
      "confidence": 0,
      "atr_pct": 0.0099,
      "reason": "low volume (0.38x avg) \u2014 skipping",
      "fib_target": null,
      "rl_action": "HOLD",
      "rl_confidence": 0.91
    },
    {
      "ticker": "NVDA",
      "action": "HOLD",
      "price": 206.27000427246094,
      "rsi": 47.69,
      "ema_trend": "BEARISH",
      "bb_signal": "IN_BAND",
      "confidence": 0,
      "atr_pct": 0.0139,
      "reason": "low volume (0.40x avg) \u2014 skipping",
      "fib_target": 192,
      "rl_action": null,
      "rl_confidence": null
    },
    {
      "ticker": "AMD",
      "action": "HOLD",
      "price": 502.0299987792969,
      "rsi": 41.05,
      "ema_trend": "BEARISH",
      "bb_signal": "IN_BAND",
      "confidence": 0,
      "atr_pct": 0.0278,
      "reason": "low volume (0.41x avg) \u2014 skipping",
      "fib_target": 515,
      "rl_action": null,
      "rl_confidence": null
    },
    {
      "ticker": "INTC",
      "action": "HOLD",
      "price": 97.16000366210938,
      "rsi": 39.91,
      "ema_trend": "BEARISH",
      "bb_signal": "IN_BAND",
      "confidence": 0,
      "atr_pct": 0.0291,
      "reason": "low volume (0.40x avg) \u2014 skipping",
      "fib_target": 120,
      "rl_action": null,
      "rl_confidence": null
    },
    {
      "ticker": "QCOM",
      "action": "HOLD",
      "price": 171.14999389648438,
      "rsi": 39.15,
      "ema_trend": "BEARISH",
      "bb_signal": "IN_BAND",
      "confidence": 0,
      "atr_pct": 0.0185,
      "reason": "low volume (0.32x avg) \u2014 skipping",
      "fib_target": null,
      "rl_action": null,
      "rl_confidence": null
    },
    {
      "ticker": "AVGO",
      "action": "HOLD",
      "price": 376.489990234375,
      "rsi": 40.84,
      "ema_trend": "BEARISH",
      "bb_signal": "IN_BAND",
      "confidence": 0,
      "atr_pct": 0.0169,
      "reason": "low volume (0.58x avg) \u2014 skipping",
      "fib_target": 334,
      "rl_action": null,
      "rl_confidence": null
    },
    {
      "ticker": "MU",
      "action": "HOLD",
      "price": 897.8900146484375,
      "rsi": 49.19,
      "ema_trend": "BEARISH",
      "bb_signal": "IN_BAND",
      "confidence": 0,
      "atr_pct": 0.033,
      "reason": "low volume (0.53x avg) \u2014 skipping",
      "fib_target": 869,
      "rl_action": null,
      "rl_confidence": null
    },
    {
      "ticker": "CRM",
      "action": "HOLD",
      "price": 170.7449951171875,
      "rsi": 53.43,
      "ema_trend": "BULLISH",
      "bb_signal": "IN_BAND",
      "confidence": 0,
      "atr_pct": 0.0116,
      "reason": "low volume (0.31x avg) \u2014 skipping",
      "fib_target": null,
      "rl_action": "BUY",
      "rl_confidence": 0.974
    },
    {
      "ticker": "AMZN",
      "action": "HOLD",
      "price": 249.0449981689453,
      "rsi": 43.8,
      "ema_trend": "BEARISH",
      "bb_signal": "IN_BAND",
      "confidence": 0,
      "atr_pct": 0.0107,
      "reason": "low volume (0.31x avg) \u2014 skipping",
      "fib_target": 230,
      "rl_action": null,
      "rl_confidence": null
    },
    {
      "ticker": "GOOGL",
      "action": "HOLD",
      "price": 346.5899963378906,
      "rsi": 29.98,
      "ema_trend": "BEARISH",
      "bb_signal": "BELOW_BAND",
      "confidence": 0,
      "atr_pct": 0.0135,
      "reason": "low volume (0.32x avg) \u2014 skipping",
      "fib_target": 357,
      "rl_action": "HOLD",
      "rl_confidence": 0.906
    },
    {
      "ticker": "META",
      "action": "HOLD",
      "price": 650.4099731445312,
      "rsi": 45.21,
      "ema_trend": "BEARISH",
      "bb_signal": "IN_BAND",
      "confidence": 0,
      "atr_pct": 0.0192,
      "reason": "RSI=45.2 (stable), BB=IN_BAND, EMA=BEARISH",
      "fib_target": null,
      "rl_action": null,
      "rl_confidence": null
    },
    {
      "ticker": "TSLA",
      "action": "HOLD",
      "price": 385.1549987792969,
      "rsi": 37.77,
      "ema_trend": "BEARISH",
      "bb_signal": "IN_BAND",
      "confidence": 0,
      "atr_pct": 0.0126,
      "reason": "low volume (0.42x avg) \u2014 skipping",
      "fib_target": 382,
      "rl_action": null,
      "rl_confidence": null
    },
    {
      "ticker": "NFLX",
      "action": "HOLD",
      "price": 69.05000305175781,
      "rsi": 31.98,
      "ema_trend": "BEARISH",
      "bb_signal": "BELOW_BAND",
      "confidence": 0,
      "atr_pct": 0.0229,
      "reason": "RSI=32.0 (stable), BB=BELOW_BAND, EMA=BEARISH",
      "fib_target": null,
      "rl_action": null,
      "rl_confidence": null
    },
    {
      "ticker": "UBER",
      "action": "HOLD",
      "price": 72.49500274658203,
      "rsi": 44.46,
      "ema_trend": "BEARISH",
      "bb_signal": "IN_BAND",
      "confidence": 0,
      "atr_pct": 0.0121,
      "reason": "RSI=44.5 (stable), BB=IN_BAND, EMA=BEARISH",
      "fib_target": null,
      "rl_action": null,
      "rl_confidence": null
    },
    {
      "ticker": "COIN",
      "action": "HOLD",
      "price": 159.22000122070312,
      "rsi": 45.33,
      "ema_trend": "BEARISH",
      "bb_signal": "IN_BAND",
      "confidence": 0,
      "atr_pct": 0.023,
      "reason": "low volume (0.30x avg) \u2014 skipping",
      "fib_target": null,
      "rl_action": null,
      "rl_confidence": null
    },
    {
      "ticker": "SNAP",
      "action": "HOLD",
      "price": 4.514999866485596,
      "rsi": 35.47,
      "ema_trend": "BEARISH",
      "bb_signal": "BELOW_BAND",
      "confidence": 0,
      "atr_pct": 0.0203,
      "reason": "low volume (0.54x avg) \u2014 skipping",
      "fib_target": null,
      "rl_action": null,
      "rl_confidence": null
    },
    {
      "ticker": "PLTR",
      "action": "HOLD",
      "price": 133.58999633789062,
      "rsi": 55.14,
      "ema_trend": "BULLISH",
      "bb_signal": "IN_BAND",
      "confidence": 0,
      "atr_pct": 0.0153,
      "reason": "low volume (0.49x avg) \u2014 skipping",
      "fib_target": 121,
      "rl_action": null,
      "rl_confidence": null
    },
    {
      "ticker": "SOFI",
      "action": "HOLD",
      "price": 17.434999465942383,
      "rsi": 41.11,
      "ema_trend": "BEARISH",
      "bb_signal": "IN_BAND",
      "confidence": 0,
      "atr_pct": 0.018,
      "reason": "low volume (0.57x avg) \u2014 skipping",
      "fib_target": null,
      "rl_action": null,
      "rl_confidence": null
    },
    {
      "ticker": "HOOD",
      "action": "HOLD",
      "price": 103.76000213623047,
      "rsi": 34.74,
      "ema_trend": "BEARISH",
      "bb_signal": "BELOW_BAND",
      "confidence": 0,
      "atr_pct": 0.0294,
      "reason": "low volume (0.48x avg) \u2014 skipping",
      "fib_target": null,
      "rl_action": null,
      "rl_confidence": null
    },
    {
      "ticker": "RIVN",
      "action": "HOLD",
      "price": 17.434999465942383,
      "rsi": 52.15,
      "ema_trend": "BEARISH",
      "bb_signal": "IN_BAND",
      "confidence": 0,
      "atr_pct": 0.0218,
      "reason": "RSI=52.2 (stable), BB=IN_BAND, EMA=BEARISH",
      "fib_target": null,
      "rl_action": null,
      "rl_confidence": null
    },
    {
      "ticker": "ARM",
      "action": "HOLD",
      "price": 270.67010498046875,
      "rsi": 47.1,
      "ema_trend": "BEARISH",
      "bb_signal": "IN_BAND",
      "confidence": 0,
      "atr_pct": 0.0333,
      "reason": "low volume (0.56x avg) \u2014 skipping",
      "fib_target": 304,
      "rl_action": null,
      "rl_confidence": null
    },
    {
      "ticker": "JPM",
      "action": "HOLD",
      "price": 343.2099914550781,
      "rsi": 50.77,
      "ema_trend": "BULLISH",
      "bb_signal": "IN_BAND",
      "confidence": 0,
      "atr_pct": 0.0085,
      "reason": "low volume (0.23x avg) \u2014 skipping",
      "fib_target": null,
      "rl_action": "HOLD",
      "rl_confidence": 0.91
    },
    {
      "ticker": "BAC",
      "action": "HOLD",
      "price": 61.459999084472656,
      "rsi": 57.28,
      "ema_trend": "BULLISH",
      "bb_signal": "IN_BAND",
      "confidence": 0,
      "atr_pct": 0.0072,
      "reason": "low volume (0.49x avg) \u2014 skipping",
      "fib_target": null,
      "rl_action": "HOLD",
      "rl_confidence": 0.918
    },
    {
      "ticker": "GS",
      "action": "HOLD",
      "price": 1080.050048828125,
      "rsi": 40.29,
      "ema_trend": "BEARISH",
      "bb_signal": "BELOW_BAND",
      "confidence": 0,
      "atr_pct": 0.0134,
      "reason": "low volume (0.20x avg) \u2014 skipping",
      "fib_target": null,
      "rl_action": null,
      "rl_confidence": null
    },
    {
      "ticker": "C",
      "action": "HOLD",
      "price": 130.07179260253906,
      "rsi": 27.02,
      "ema_trend": "BEARISH",
      "bb_signal": "BELOW_BAND",
      "confidence": 0,
      "atr_pct": 0.0109,
      "reason": "low volume (0.25x avg) \u2014 skipping",
      "fib_target": null,
      "rl_action": "HOLD",
      "rl_confidence": 0.906
    },
    {
      "ticker": "WFC",
      "action": "HOLD",
      "price": 88.04499816894531,
      "rsi": 54.93,
      "ema_trend": "BULLISH",
      "bb_signal": "IN_BAND",
      "confidence": 0,
      "atr_pct": 0.0106,
      "reason": "low volume (0.39x avg) \u2014 skipping",
      "fib_target": null,
      "rl_action": "BUY",
      "rl_confidence": 0.974
    },
    {
      "ticker": "JNJ",
      "action": "HOLD",
      "price": 252.72000122070312,
      "rsi": 50.58,
      "ema_trend": "NEUTRAL",
      "bb_signal": "IN_BAND",
      "confidence": 0,
      "atr_pct": 0.0098,
      "reason": "low volume (0.42x avg) \u2014 skipping",
      "fib_target": null,
      "rl_action": null,
      "rl_confidence": null
    },
    {
      "ticker": "PFE",
      "action": "HOLD",
      "price": 25.094999313354492,
      "rsi": 60.32,
      "ema_trend": "BULLISH",
      "bb_signal": "IN_BAND",
      "confidence": 0,
      "atr_pct": 0.0074,
      "reason": "low volume (0.43x avg) \u2014 skipping",
      "fib_target": null,
      "rl_action": "HOLD",
      "rl_confidence": 0.918
    },
    {
      "ticker": "MRNA",
      "action": "HOLD",
      "price": 63.06999969482422,
      "rsi": 31.89,
      "ema_trend": "BEARISH",
      "bb_signal": "IN_BAND",
      "confidence": 0,
      "atr_pct": 0.0195,
      "reason": "low volume (0.32x avg) \u2014 skipping",
      "fib_target": null,
      "rl_action": null,
      "rl_confidence": null
    },
    {
      "ticker": "DIS",
      "action": "HOLD",
      "price": 97.61000061035156,
      "rsi": 48.94,
      "ema_trend": "BULLISH",
      "bb_signal": "IN_BAND",
      "confidence": 0,
      "atr_pct": 0.0069,
      "reason": "low volume (0.40x avg) \u2014 skipping",
      "fib_target": null,
      "rl_action": "HOLD",
      "rl_confidence": 0.91
    },
    {
      "ticker": "SBUX",
      "action": "HOLD",
      "price": 106.18000030517578,
      "rsi": 43.3,
      "ema_trend": "NEUTRAL",
      "bb_signal": "IN_BAND",
      "confidence": 0,
      "atr_pct": 0.01,
      "reason": "low volume (0.42x avg) \u2014 skipping",
      "fib_target": null,
      "rl_action": null,
      "rl_confidence": null
    },
    {
      "ticker": "MCD",
      "action": "HOLD",
      "price": 268.3970031738281,
      "rsi": 40.29,
      "ema_trend": "NEUTRAL",
      "bb_signal": "IN_BAND",
      "confidence": 0,
      "atr_pct": 0.0082,
      "reason": "low volume (0.34x avg) \u2014 skipping",
      "fib_target": null,
      "rl_action": null,
      "rl_confidence": null
    },
    {
      "ticker": "WMT",
      "action": "HOLD",
      "price": 114.16500091552734,
      "rsi": 48.31,
      "ema_trend": "BULLISH",
      "bb_signal": "IN_BAND",
      "confidence": 0,
      "atr_pct": 0.0099,
      "reason": "low volume (0.50x avg) \u2014 skipping",
      "fib_target": null,
      "rl_action": "HOLD",
      "rl_confidence": 0.91
    },
    {
      "ticker": "TGT",
      "action": "HOLD",
      "price": 139.52499389648438,
      "rsi": 54.15,
      "ema_trend": "BULLISH",
      "bb_signal": "IN_BAND",
      "confidence": 0,
      "atr_pct": 0.0113,
      "reason": "low volume (0.39x avg) \u2014 skipping",
      "fib_target": null,
      "rl_action": "BUY",
      "rl_confidence": 0.974
    },
    {
      "ticker": "BA",
      "action": "HOLD",
      "price": 215.21499633789062,
      "rsi": 41.38,
      "ema_trend": "BEARISH",
      "bb_signal": "IN_BAND",
      "confidence": 0,
      "atr_pct": 0.0086,
      "reason": "low volume (0.31x avg) \u2014 skipping",
      "fib_target": null,
      "rl_action": null,
      "rl_confidence": null
    },
    {
      "ticker": "GE",
      "action": "HOLD",
      "price": 353.9150085449219,
      "rsi": 52.49,
      "ema_trend": "BEARISH",
      "bb_signal": "IN_BAND",
      "confidence": 0,
      "atr_pct": 0.0133,
      "reason": "low volume (0.28x avg) \u2014 skipping",
      "fib_target": null,
      "rl_action": null,
      "rl_confidence": null
    },
    {
      "ticker": "F",
      "action": "HOLD",
      "price": 14.444999694824219,
      "rsi": 67.09,
      "ema_trend": "BULLISH",
      "bb_signal": "ABOVE_BAND",
      "confidence": 0,
      "atr_pct": 0.0116,
      "reason": "low volume (0.65x avg) \u2014 skipping",
      "fib_target": null,
      "rl_action": null,
      "rl_confidence": null
    },
    {
      "ticker": "GM",
      "action": "HOLD",
      "price": 77.11000061035156,
      "rsi": 50.18,
      "ema_trend": "NEUTRAL",
      "bb_signal": "IN_BAND",
      "confidence": 0,
      "atr_pct": 0.0081,
      "reason": "low volume (0.47x avg) \u2014 skipping",
      "fib_target": null,
      "rl_action": null,
      "rl_confidence": null
    },
    {
      "ticker": "XOM",
      "action": "HOLD",
      "price": 147.8699951171875,
      "rsi": 65.4,
      "ema_trend": "BULLISH",
      "bb_signal": "ABOVE_BAND",
      "confidence": 0,
      "atr_pct": 0.0081,
      "reason": "low volume (0.60x avg) \u2014 skipping",
      "fib_target": null,
      "rl_action": "HOLD",
      "rl_confidence": 0.918
    },
    {
      "ticker": "CVX",
      "action": "HOLD",
      "price": 186.08999633789062,
      "rsi": 69.39,
      "ema_trend": "BULLISH",
      "bb_signal": "ABOVE_BAND",
      "confidence": 0,
      "atr_pct": 0.0068,
      "reason": "low volume (0.38x avg) \u2014 skipping",
      "fib_target": null,
      "rl_action": "HOLD",
      "rl_confidence": 0.918
    },
    {
      "ticker": "PYPL",
      "action": "HOLD",
      "price": 56.83000183105469,
      "rsi": 76.02,
      "ema_trend": "BULLISH",
      "bb_signal": "IN_BAND",
      "confidence": 0,
      "atr_pct": 0.0128,
      "reason": "low volume (0.14x avg) \u2014 skipping",
      "fib_target": null,
      "rl_action": null,
      "rl_confidence": null
    },
    {
      "ticker": "SHOP",
      "action": "HOLD",
      "price": 123.11000061035156,
      "rsi": 44.02,
      "ema_trend": "BEARISH",
      "bb_signal": "BELOW_BAND",
      "confidence": 0,
      "atr_pct": 0.016,
      "reason": "low volume (0.29x avg) \u2014 skipping",
      "fib_target": null,
      "rl_action": null,
      "rl_confidence": null
    },
    {
      "ticker": "RBLX",
      "action": "HOLD",
      "price": 52.5,
      "rsi": 33.95,
      "ema_trend": "BEARISH",
      "bb_signal": "BELOW_BAND",
      "confidence": 0,
      "atr_pct": 0.0202,
      "reason": "low volume (0.28x avg) \u2014 skipping",
      "fib_target": null,
      "rl_action": null,
      "rl_confidence": null
    },
    {
      "ticker": "DKNG",
      "action": "HOLD",
      "price": 24.844999313354492,
      "rsi": 42.57,
      "ema_trend": "BEARISH",
      "bb_signal": "IN_BAND",
      "confidence": 0,
      "atr_pct": 0.0175,
      "reason": "low volume (0.59x avg) \u2014 skipping",
      "fib_target": null,
      "rl_action": null,
      "rl_confidence": null
    },
    {
      "ticker": "ORCL",
      "action": "HOLD",
      "price": 128.27000427246094,
      "rsi": 44.8,
      "ema_trend": "BEARISH",
      "bb_signal": "IN_BAND",
      "confidence": 0,
      "atr_pct": 0.0159,
      "reason": "low volume (0.30x avg) \u2014 skipping",
      "fib_target": null,
      "rl_action": null,
      "rl_confidence": null
    },
    {
      "ticker": "SNOW",
      "action": "HOLD",
      "price": 267.94000244140625,
      "rsi": 46.16,
      "ema_trend": "BEARISH",
      "bb_signal": "IN_BAND",
      "confidence": 0,
      "atr_pct": 0.0193,
      "reason": "low volume (0.36x avg) \u2014 skipping",
      "fib_target": 181,
      "rl_action": null,
      "rl_confidence": null
    },
    {
      "ticker": "AI",
      "action": "HOLD",
      "price": 9.074999809265137,
      "rsi": 51.61,
      "ema_trend": "BEARISH",
      "bb_signal": "IN_BAND",
      "confidence": 0,
      "atr_pct": 0.0201,
      "reason": "low volume (0.55x avg) \u2014 skipping",
      "fib_target": null,
      "rl_action": null,
      "rl_confidence": null
    },
    {
      "ticker": "SOUN",
      "action": "HOLD",
      "price": 6.385000228881836,
      "rsi": 49.12,
      "ema_trend": "BEARISH",
      "bb_signal": "IN_BAND",
      "confidence": 0,
      "atr_pct": 0.0231,
      "reason": "RSI=49.1 (stable), BB=IN_BAND, EMA=BEARISH",
      "fib_target": null,
      "rl_action": null,
      "rl_confidence": null
    },
    {
      "ticker": "SMCI",
      "action": "HOLD",
      "price": 25.100000381469727,
      "rsi": 39.03,
      "ema_trend": "BEARISH",
      "bb_signal": "IN_BAND",
      "confidence": 0,
      "atr_pct": 0.0266,
      "reason": "low volume (0.56x avg) \u2014 skipping",
      "fib_target": null,
      "rl_action": null,
      "rl_confidence": null
    },
    {
      "ticker": "VRT",
      "action": "HOLD",
      "price": 296.0899963378906,
      "rsi": 47.61,
      "ema_trend": "BEARISH",
      "bb_signal": "IN_BAND",
      "confidence": 0,
      "atr_pct": 0.0232,
      "reason": "low volume (0.42x avg) \u2014 skipping",
      "fib_target": 282,
      "rl_action": null,
      "rl_confidence": null
    },
    {
      "ticker": "DELL",
      "action": "HOLD",
      "price": 404.489990234375,
      "rsi": 45.73,
      "ema_trend": "BEARISH",
      "bb_signal": "IN_BAND",
      "confidence": 0,
      "atr_pct": 0.028,
      "reason": "low volume (0.35x avg) \u2014 skipping",
      "fib_target": null,
      "rl_action": null,
      "rl_confidence": null
    },
    {
      "ticker": "EQIX",
      "action": "HOLD",
      "price": 1018.3900146484375,
      "rsi": 50.03,
      "ema_trend": "BEARISH",
      "bb_signal": "IN_BAND",
      "confidence": 0,
      "atr_pct": 0.0093,
      "reason": "low volume (0.30x avg) \u2014 skipping",
      "fib_target": null,
      "rl_action": null,
      "rl_confidence": null
    },
    {
      "ticker": "AMAT",
      "action": "HOLD",
      "price": 547.5900268554688,
      "rsi": 37.89,
      "ema_trend": "BEARISH",
      "bb_signal": "IN_BAND",
      "confidence": 0,
      "atr_pct": 0.0261,
      "reason": "low volume (0.54x avg) \u2014 skipping",
      "fib_target": null,
      "rl_action": null,
      "rl_confidence": null
    },
    {
      "ticker": "LRCX",
      "action": "HOLD",
      "price": 318.4849853515625,
      "rsi": 41.27,
      "ema_trend": "BEARISH",
      "bb_signal": "IN_BAND",
      "confidence": 0,
      "atr_pct": 0.0262,
      "reason": "low volume (0.56x avg) \u2014 skipping",
      "fib_target": null,
      "rl_action": null,
      "rl_confidence": null
    },
    {
      "ticker": "KLAC",
      "action": "HOLD",
      "price": 216.60000610351562,
      "rsi": 43.19,
      "ema_trend": "BEARISH",
      "bb_signal": "IN_BAND",
      "confidence": 0,
      "atr_pct": 0.0256,
      "reason": "low volume (0.50x avg) \u2014 skipping",
      "fib_target": null,
      "rl_action": null,
      "rl_confidence": null
    },
    {
      "ticker": "MRVL",
      "action": "HOLD",
      "price": 193.9499969482422,
      "rsi": 38.09,
      "ema_trend": "BEARISH",
      "bb_signal": "IN_BAND",
      "confidence": 0,
      "atr_pct": 0.0315,
      "reason": "low volume (0.46x avg) \u2014 skipping",
      "fib_target": 225,
      "rl_action": null,
      "rl_confidence": null
    },
    {
      "ticker": "TXN",
      "action": "HOLD",
      "price": 288.7300109863281,
      "rsi": 39.86,
      "ema_trend": "BEARISH",
      "bb_signal": "IN_BAND",
      "confidence": 0,
      "atr_pct": 0.0184,
      "reason": "low volume (0.44x avg) \u2014 skipping",
      "fib_target": null,
      "rl_action": null,
      "rl_confidence": null
    },
    {
      "ticker": "ASML",
      "action": "HOLD",
      "price": 1788.1949462890625,
      "rsi": 51.44,
      "ema_trend": "BEARISH",
      "bb_signal": "IN_BAND",
      "confidence": 0,
      "atr_pct": 0.0177,
      "reason": "low volume (0.18x avg) \u2014 skipping",
      "fib_target": 1732,
      "rl_action": null,
      "rl_confidence": null
    },
    {
      "ticker": "RKLB",
      "action": "HOLD",
      "price": 70.33000183105469,
      "rsi": 39.34,
      "ema_trend": "BEARISH",
      "bb_signal": "IN_BAND",
      "confidence": 0,
      "atr_pct": 0.0332,
      "reason": "low volume (0.42x avg) \u2014 skipping",
      "fib_target": 92,
      "rl_action": null,
      "rl_confidence": null
    },
    {
      "ticker": "ASTS",
      "action": "HOLD",
      "price": 60.9900016784668,
      "rsi": 45.55,
      "ema_trend": "BEARISH",
      "bb_signal": "IN_BAND",
      "confidence": 0,
      "atr_pct": 0.0425,
      "reason": "low volume (0.44x avg) \u2014 skipping",
      "fib_target": 79,
      "rl_action": null,
      "rl_confidence": null
    },
    {
      "ticker": "PL",
      "action": "HOLD",
      "price": 23.125,
      "rsi": 39.42,
      "ema_trend": "BEARISH",
      "bb_signal": "IN_BAND",
      "confidence": 0,
      "atr_pct": 0.029,
      "reason": "low volume (0.29x avg) \u2014 skipping",
      "fib_target": 26,
      "rl_action": null,
      "rl_confidence": null
    },
    {
      "ticker": "RDW",
      "action": "HOLD",
      "price": 8.710100173950195,
      "rsi": 35.18,
      "ema_trend": "BEARISH",
      "bb_signal": "IN_BAND",
      "confidence": 0,
      "atr_pct": 0.0275,
      "reason": "low volume (0.23x avg) \u2014 skipping",
      "fib_target": 8,
      "rl_action": null,
      "rl_confidence": null
    },
    {
      "ticker": "ISRG",
      "action": "HOLD",
      "price": 350.82000732421875,
      "rsi": 21.29,
      "ema_trend": "BEARISH",
      "bb_signal": "BELOW_BAND",
      "confidence": 0,
      "atr_pct": 0.0244,
      "reason": "low volume (0.56x avg) \u2014 skipping",
      "fib_target": 397,
      "rl_action": "HOLD",
      "rl_confidence": 0.93
    },
    {
      "ticker": "SYM",
      "action": "HOLD",
      "price": 42.20500183105469,
      "rsi": 46.88,
      "ema_trend": "BEARISH",
      "bb_signal": "IN_BAND",
      "confidence": 0,
      "atr_pct": 0.0218,
      "reason": "low volume (0.42x avg) \u2014 skipping",
      "fib_target": null,
      "rl_action": null,
      "rl_confidence": null
    },
    {
      "ticker": "MBLY",
      "action": "HOLD",
      "price": 9.298199653625488,
      "rsi": 46.62,
      "ema_trend": "BEARISH",
      "bb_signal": "IN_BAND",
      "confidence": 0,
      "atr_pct": 0.0211,
      "reason": "low volume (0.16x avg) \u2014 skipping",
      "fib_target": null,
      "rl_action": null,
      "rl_confidence": null
    },
    {
      "ticker": "TER",
      "action": "HOLD",
      "price": 328.82000732421875,
      "rsi": 46.01,
      "ema_trend": "BEARISH",
      "bb_signal": "IN_BAND",
      "confidence": 0,
      "atr_pct": 0.032,
      "reason": "ATR too high (3.2%) \u2014 skipping",
      "fib_target": null,
      "rl_action": null,
      "rl_confidence": null
    },
    {
      "ticker": "ROK",
      "action": "HOLD",
      "price": 462.1199951171875,
      "rsi": 46.97,
      "ema_trend": "BEARISH",
      "bb_signal": "IN_BAND",
      "confidence": 0,
      "atr_pct": 0.0116,
      "reason": "low volume (0.65x avg) \u2014 skipping",
      "fib_target": null,
      "rl_action": null,
      "rl_confidence": null
    },
    {
      "ticker": "AUR",
      "action": "HOLD",
      "price": 6.03000020980835,
      "rsi": 51.86,
      "ema_trend": "BEARISH",
      "bb_signal": "IN_BAND",
      "confidence": 0,
      "atr_pct": 0.0204,
      "reason": "low volume (0.37x avg) \u2014 skipping",
      "fib_target": null,
      "rl_action": null,
      "rl_confidence": null
    },
    {
      "ticker": "LAZR",
      "action": "HOLD",
      "price": 37.900001525878906,
      "rsi": 34.98,
      "ema_trend": "BEARISH",
      "bb_signal": "IN_BAND",
      "confidence": 0,
      "atr_pct": 0.0234,
      "reason": "low volume (0.43x avg) \u2014 skipping",
      "fib_target": null,
      "rl_action": null,
      "rl_confidence": null
    },
    {
      "ticker": "IONQ",
      "action": "HOLD",
      "price": 35.80500030517578,
      "rsi": 38.17,
      "ema_trend": "BEARISH",
      "bb_signal": "IN_BAND",
      "confidence": 0,
      "atr_pct": 0.026,
      "reason": "low volume (0.39x avg) \u2014 skipping",
      "fib_target": 44,
      "rl_action": null,
      "rl_confidence": null
    },
    {
      "ticker": "RGTI",
      "action": "HOLD",
      "price": 14.5,
      "rsi": 40.76,
      "ema_trend": "BEARISH",
      "bb_signal": "IN_BAND",
      "confidence": 0,
      "atr_pct": 0.0282,
      "reason": "low volume (0.63x avg) \u2014 skipping",
      "fib_target": 16,
      "rl_action": null,
      "rl_confidence": null
    },
    {
      "ticker": "QBTS",
      "action": "HOLD",
      "price": 17.329999923706055,
      "rsi": 39.37,
      "ema_trend": "BEARISH",
      "bb_signal": "IN_BAND",
      "confidence": 0,
      "atr_pct": 0.0265,
      "reason": "low volume (0.61x avg) \u2014 skipping",
      "fib_target": 20,
      "rl_action": null,
      "rl_confidence": null
    },
    {
      "ticker": "INFQ",
      "action": "HOLD",
      "price": 9.388500213623047,
      "rsi": 40.98,
      "ema_trend": "BEARISH",
      "bb_signal": "IN_BAND",
      "confidence": 0,
      "atr_pct": 0.0283,
      "reason": "low volume (0.35x avg) \u2014 skipping",
      "fib_target": 10,
      "rl_action": null,
      "rl_confidence": null
    },
    {
      "ticker": "ONDS",
      "action": "HOLD",
      "price": 6.715000152587891,
      "rsi": 44.71,
      "ema_trend": "BEARISH",
      "bb_signal": "IN_BAND",
      "confidence": 0,
      "atr_pct": 0.0309,
      "reason": "ATR too high (3.1%) \u2014 skipping",
      "fib_target": 7,
      "rl_action": null,
      "rl_confidence": null
    },
    {
      "ticker": "AVAV",
      "action": "HOLD",
      "price": 146.85000610351562,
      "rsi": 51.6,
      "ema_trend": "BULLISH",
      "bb_signal": "IN_BAND",
      "confidence": 0,
      "atr_pct": 0.0256,
      "reason": "low volume (0.30x avg) \u2014 skipping",
      "fib_target": 174,
      "rl_action": "BUY",
      "rl_confidence": 1.0
    },
    {
      "ticker": "KTOS",
      "action": "HOLD",
      "price": 46.82500076293945,
      "rsi": 41.18,
      "ema_trend": "BEARISH",
      "bb_signal": "IN_BAND",
      "confidence": 0,
      "atr_pct": 0.0216,
      "reason": "low volume (0.29x avg) \u2014 skipping",
      "fib_target": 52,
      "rl_action": null,
      "rl_confidence": null
    },
    {
      "ticker": "MRCY",
      "action": "HOLD",
      "price": 98.87000274658203,
      "rsi": 42.69,
      "ema_trend": "BEARISH",
      "bb_signal": "IN_BAND",
      "confidence": 0,
      "atr_pct": 0.0221,
      "reason": "low volume (0.46x avg) \u2014 skipping",
      "fib_target": 104,
      "rl_action": null,
      "rl_confidence": null
    },
    {
      "ticker": "OKLO",
      "action": "HOLD",
      "price": 42.439998626708984,
      "rsi": 41.85,
      "ema_trend": "BEARISH",
      "bb_signal": "IN_BAND",
      "confidence": 0,
      "atr_pct": 0.0283,
      "reason": "low volume (0.48x avg) \u2014 skipping",
      "fib_target": 50,
      "rl_action": null,
      "rl_confidence": null
    },
    {
      "ticker": "UUUU",
      "action": "HOLD",
      "price": 11.734999656677246,
      "rsi": 34.29,
      "ema_trend": "BEARISH",
      "bb_signal": "IN_BAND",
      "confidence": 0,
      "atr_pct": 0.022,
      "reason": "low volume (0.30x avg) \u2014 skipping",
      "fib_target": 12,
      "rl_action": null,
      "rl_confidence": null
    },
    {
      "ticker": "GEV",
      "action": "HOLD",
      "price": 1063.425048828125,
      "rsi": 56.56,
      "ema_trend": "NEUTRAL",
      "bb_signal": "ABOVE_BAND",
      "confidence": 0,
      "atr_pct": 0.0212,
      "reason": "low volume (0.50x avg) \u2014 skipping",
      "fib_target": 906,
      "rl_action": null,
      "rl_confidence": null
    },
    {
      "ticker": "LEU",
      "action": "HOLD",
      "price": 155.33999633789062,
      "rsi": 52.15,
      "ema_trend": "BEARISH",
      "bb_signal": "IN_BAND",
      "confidence": 0,
      "atr_pct": 0.0252,
      "reason": "low volume (0.48x avg) \u2014 skipping",
      "fib_target": 132,
      "rl_action": null,
      "rl_confidence": null
    },
    {
      "ticker": "AAOI",
      "action": "HOLD",
      "price": 104.55999755859375,
      "rsi": 43.67,
      "ema_trend": "BEARISH",
      "bb_signal": "IN_BAND",
      "confidence": 0,
      "atr_pct": 0.0425,
      "reason": "low volume (0.31x avg) \u2014 skipping",
      "fib_target": 103,
      "rl_action": null,
      "rl_confidence": null
    },
    {
      "ticker": "LITE",
      "action": "HOLD",
      "price": 741.6649780273438,
      "rsi": 50.34,
      "ema_trend": "BEARISH",
      "bb_signal": "IN_BAND",
      "confidence": 0,
      "atr_pct": 0.0347,
      "reason": "low volume (0.51x avg) \u2014 skipping",
      "fib_target": 636,
      "rl_action": null,
      "rl_confidence": null
    },
    {
      "ticker": "COHR",
      "action": "HOLD",
      "price": 283.989990234375,
      "rsi": 41.89,
      "ema_trend": "BEARISH",
      "bb_signal": "IN_BAND",
      "confidence": 0,
      "atr_pct": 0.0293,
      "reason": "low volume (0.47x avg) \u2014 skipping",
      "fib_target": 311,
      "rl_action": null,
      "rl_confidence": null
    },
    {
      "ticker": "AEHR",
      "action": "HOLD",
      "price": 83.49500274658203,
      "rsi": 55.29,
      "ema_trend": "BULLISH",
      "bb_signal": "IN_BAND",
      "confidence": 0,
      "atr_pct": 0.0563,
      "reason": "low volume (0.24x avg) \u2014 skipping",
      "fib_target": 59,
      "rl_action": null,
      "rl_confidence": null
    },
    {
      "ticker": "AMKR",
      "action": "HOLD",
      "price": 63.4900016784668,
      "rsi": 42.59,
      "ema_trend": "BEARISH",
      "bb_signal": "IN_BAND",
      "confidence": 0,
      "atr_pct": 0.0307,
      "reason": "low volume (0.41x avg) \u2014 skipping",
      "fib_target": 64,
      "rl_action": null,
      "rl_confidence": null
    },
    {
      "ticker": "TSM",
      "action": "HOLD",
      "price": 404.17999267578125,
      "rsi": 37.46,
      "ema_trend": "BEARISH",
      "bb_signal": "IN_BAND",
      "confidence": 0,
      "atr_pct": 0.0183,
      "reason": "low volume (0.33x avg) \u2014 skipping",
      "fib_target": 419,
      "rl_action": null,
      "rl_confidence": null
    },
    {
      "ticker": "IREN",
      "action": "HOLD",
      "price": 34.5,
      "rsi": 35.41,
      "ema_trend": "BEARISH",
      "bb_signal": "IN_BAND",
      "confidence": 0,
      "atr_pct": 0.0365,
      "reason": "low volume (0.49x avg) \u2014 skipping",
      "fib_target": 31,
      "rl_action": null,
      "rl_confidence": null
    },
    {
      "ticker": "NBIS",
      "action": "HOLD",
      "price": 182.82000732421875,
      "rsi": 43.0,
      "ema_trend": "BEARISH",
      "bb_signal": "IN_BAND",
      "confidence": 0,
      "atr_pct": 0.0453,
      "reason": "low volume (0.39x avg) \u2014 skipping",
      "fib_target": 213,
      "rl_action": null,
      "rl_confidence": null
    },
    {
      "ticker": "CIFR",
      "action": "HOLD",
      "price": 17.7549991607666,
      "rsi": 38.82,
      "ema_trend": "BEARISH",
      "bb_signal": "IN_BAND",
      "confidence": 0,
      "atr_pct": 0.0438,
      "reason": "low volume (0.55x avg) \u2014 skipping",
      "fib_target": 17,
      "rl_action": null,
      "rl_confidence": null
    },
    {
      "ticker": "CRWV",
      "action": "HOLD",
      "price": 73.66600036621094,
      "rsi": 35.64,
      "ema_trend": "BEARISH",
      "bb_signal": "IN_BAND",
      "confidence": 0,
      "atr_pct": 0.0311,
      "reason": "low volume (0.39x avg) \u2014 skipping",
      "fib_target": 67,
      "rl_action": null,
      "rl_confidence": null
    },
    {
      "ticker": "EOSE",
      "action": "HOLD",
      "price": 4.295000076293945,
      "rsi": 51.78,
      "ema_trend": "BEARISH",
      "bb_signal": "IN_BAND",
      "confidence": 0,
      "atr_pct": 0.0426,
      "reason": "low volume (0.19x avg) \u2014 skipping",
      "fib_target": 4,
      "rl_action": null,
      "rl_confidence": null
    },
    {
      "ticker": "BE",
      "action": "HOLD",
      "price": 221.31500244140625,
      "rsi": 46.81,
      "ema_trend": "BEARISH",
      "bb_signal": "IN_BAND",
      "confidence": 0,
      "atr_pct": 0.039,
      "reason": "low volume (0.41x avg) \u2014 skipping",
      "fib_target": 265,
      "rl_action": null,
      "rl_confidence": null
    },
    {
      "ticker": "NVTS",
      "action": "HOLD",
      "price": 11.975000381469727,
      "rsi": 41.43,
      "ema_trend": "BEARISH",
      "bb_signal": "IN_BAND",
      "confidence": 0,
      "atr_pct": 0.0399,
      "reason": "low volume (0.40x avg) \u2014 skipping",
      "fib_target": 13,
      "rl_action": null,
      "rl_confidence": null
    },
    {
      "ticker": "ALAB",
      "action": "HOLD",
      "price": 311.8504943847656,
      "rsi": 34.52,
      "ema_trend": "BEARISH",
      "bb_signal": "IN_BAND",
      "confidence": 0,
      "atr_pct": 0.0404,
      "reason": "ATR too high (4.0%) \u2014 skipping",
      "fib_target": 341,
      "rl_action": null,
      "rl_confidence": null
    },
    {
      "ticker": "CRDO",
      "action": "HOLD",
      "price": 207.5,
      "rsi": 40.82,
      "ema_trend": "BEARISH",
      "bb_signal": "IN_BAND",
      "confidence": 0,
      "atr_pct": 0.0423,
      "reason": "low volume (0.56x avg) \u2014 skipping",
      "fib_target": 210,
      "rl_action": null,
      "rl_confidence": null
    },
    {
      "ticker": "NOW",
      "action": "HOLD",
      "price": 104.14920043945312,
      "rsi": 46.54,
      "ema_trend": "BEARISH",
      "bb_signal": "IN_BAND",
      "confidence": 0,
      "atr_pct": 0.0164,
      "reason": "low volume (0.32x avg) \u2014 skipping",
      "fib_target": 104,
      "rl_action": null,
      "rl_confidence": null
    },
    {
      "ticker": "CRWD",
      "action": "HOLD",
      "price": 206.22000122070312,
      "rsi": 57.14,
      "ema_trend": "BULLISH",
      "bb_signal": "IN_BAND",
      "confidence": 0,
      "atr_pct": 0.0166,
      "reason": "low volume (0.24x avg) \u2014 skipping",
      "fib_target": 171,
      "rl_action": null,
      "rl_confidence": null
    }
  ],
  "fib_targets": {
    "RKLB": 92,
    "ASTS": 79,
    "PL": 26,
    "RDW": 8,
    "IONQ": 44,
    "RGTI": 16,
    "QBTS": 20,
    "INFQ": 10,
    "ONDS": 7,
    "AVAV": 174,
    "KTOS": 52,
    "MRCY": 104,
    "OKLO": 50,
    "UUUU": 12,
    "GEV": 906,
    "LEU": 132,
    "AAOI": 103,
    "LITE": 636,
    "COHR": 311,
    "AEHR": 59,
    "AMD": 515,
    "INTC": 120,
    "ARM": 304,
    "AMKR": 64,
    "TSLA": 382,
    "AMZN": 230,
    "GOOGL": 357,
    "ISRG": 397,
    "IREN": 31,
    "NBIS": 213,
    "CIFR": 17,
    "CRWV": 67,
    "EOSE": 4,
    "BE": 265,
    "NVTS": 13,
    "VRT": 282,
    "AVGO": 334,
    "ALAB": 341,
    "CRDO": 210,
    "MRVL": 225,
    "NVDA": 192,
    "TSM": 419,
    "ASML": 1732,
    "MU": 869,
    "PLTR": 121,
    "NOW": 104,
    "CRWD": 171,
    "SNOW": 181
  },
  "sector_groups": {
    "Space": [
      "RKLB",
      "ASTS",
      "PL",
      "RDW"
    ],
    "Quantum": [
      "IONQ",
      "RGTI",
      "QBTS",
      "INFQ"
    ],
    "Drones": [
      "ONDS",
      "AVAV",
      "KTOS",
      "MRCY"
    ],
    "Nuclear": [
      "OKLO",
      "UUUU",
      "GEV",
      "LEU"
    ],
    "Photonics": [
      "AAOI",
      "LITE",
      "COHR",
      "AEHR"
    ],
    "CPU": [
      "AMD",
      "INTC",
      "ARM",
      "AMKR"
    ],
    "Physical AI": [
      "TSLA",
      "AMZN",
      "GOOGL",
      "ISRG"
    ],
    "AI Utilities": [
      "IREN",
      "NBIS",
      "CIFR",
      "CRWV"
    ],
    "AI Power": [
      "EOSE",
      "BE",
      "NVTS",
      "VRT"
    ],
    "AI Connectivity": [
      "AVGO",
      "ALAB",
      "CRDO",
      "MRVL"
    ],
    "AI Hardware": [
      "NVDA",
      "TSM",
      "ASML",
      "MU"
    ],
    "AI Applications": [
      "PLTR",
      "NOW",
      "CRWD",
      "SNOW"
    ]
  },
  "rl_stats": {
    "live": true,
    "states": 19,
    "training_samples": 392
  },
  "net_buy_buy_signals": [],
  "net_buy_sell_signals": [
    {
      "ticker": "JNJ",
      "price": 252.52000427246094,
      "net_buy_d2": 137672,
      "net_buy_d3": -3106264,
      "obv_slope": -717538,
      "score": 0.0,
      "reason": "Net buy reversed: 0.14M \u2192 -3.11M | OBV -0.7M/day"
    },
    {
      "ticker": "AEP",
      "price": 132.35499572753906,
      "net_buy_d2": 777705,
      "net_buy_d3": -1825688,
      "obv_slope": -1141034,
      "score": 0.0,
      "reason": "Net buy reversed: 0.78M \u2192 -1.83M | OBV -1.1M/day"
    },
    {
      "ticker": "FAST",
      "price": 45.59510040283203,
      "net_buy_d2": 1722850,
      "net_buy_d3": -3359670,
      "obv_slope": -5099605,
      "score": 0.0,
      "reason": "Net buy reversed: 1.72M \u2192 -3.36M | OBV -5.1M/day"
    },
    {
      "ticker": "WMT",
      "price": 114.16999816894531,
      "net_buy_d2": 7660386,
      "net_buy_d3": -10654341,
      "obv_slope": -3876196,
      "score": 0.0,
      "reason": "Net buy reversed: 7.66M \u2192 -10.65M | OBV -3.9M/day"
    },
    {
      "ticker": "SRE",
      "price": 92.69499969482422,
      "net_buy_d2": 981219,
      "net_buy_d3": -1124345,
      "obv_slope": -775630,
      "score": 0.0,
      "reason": "Net buy reversed: 0.98M \u2192 -1.12M | OBV -0.8M/day"
    },
    {
      "ticker": "AIZ",
      "price": 277.7799987792969,
      "net_buy_d2": 83273,
      "net_buy_d3": -90664,
      "obv_slope": -33317,
      "score": 0.0,
      "reason": "Net buy reversed: 0.08M \u2192 -0.09M | OBV -0.0M/day"
    },
    {
      "ticker": "CVX",
      "price": 186.07000732421875,
      "net_buy_d2": 2040226,
      "net_buy_d3": -2083720,
      "obv_slope": -781719,
      "score": 0.0,
      "reason": "Net buy reversed: 2.04M \u2192 -2.08M | OBV -0.8M/day"
    },
    {
      "ticker": "TDG",
      "price": 1222.864990234375,
      "net_buy_d2": 69096,
      "net_buy_d3": -69580,
      "obv_slope": -74047,
      "score": 0.0,
      "reason": "Net buy reversed: 0.07M \u2192 -0.07M | OBV -0.1M/day"
    },
    {
      "ticker": "OKE",
      "price": 92.8644027709961,
      "net_buy_d2": 1396816,
      "net_buy_d3": -1341227,
      "obv_slope": -939768,
      "score": 0.0,
      "reason": "Net buy reversed: 1.40M \u2192 -1.34M | OBV -0.9M/day"
    },
    {
      "ticker": "L",
      "price": 114.59850311279297,
      "net_buy_d2": 301953,
      "net_buy_d3": -267997,
      "obv_slope": -108041,
      "score": 0.0,
      "reason": "Net buy reversed: 0.30M \u2192 -0.27M | OBV -0.1M/day"
    }
  ],
  "surge_signals": []
}